[
  {
    "session_id": "2407c339-6e60-4ade-9437-9441365dfc4e",
    "timestamp": "2026-05-04T09:23:20.160734+00:00",
    "location": null,
    "complaint_text": "I understand you need medical help, is that correct?",
    "intent": "Medical",
    "urgency": 4,
    "distress_level": 2,
    "language": "en",
    "acoustic_data": {
      "environment": "moderate",
      "loudness": "normal"
    }
  },
  {
    "id": "a166b902-8384-4048-a4d9-35ab3c025d88",
    "timestamp": "2026-05-04T09:50:15.844175+00:00",
    "location": "en",
    "issue": "Du har en brandkatastrofe.",
    "urgency": 4,
    "status": "Pending Dispatch"
  },
  {
    "id": "ffc04364-52a0-4168-a340-8af0e9783722",
    "timestamp": "2026-05-04T09:54:14.067884+00:00",
    "location": "house",
    "issue": "The entire incident is happening at a house.",
    "urgency": 3,
    "status": "Pending Dispatch"
  },
  {
    "id": "11107593-e4ea-4419-ac93-7ff76ea35464",
    "timestamp": "2026-05-04T09:55:07.788342+00:00",
    "location": "Your house",
    "issue": "Your house is on fire.",
    "urgency": 4,
    "status": "Pending Dispatch"
  },
  {
    "id": "ed014660-d81d-4be1-a468-9c88348f209d",
    "timestamp": "2026-05-04T09:55:39.941919+00:00",
    "location": "en",
    "issue": "The water supply has been cut off for four days.",
    "urgency": 3,
    "status": "Pending Dispatch"
  },
  {
    "id": "f30e3fc1-92ac-4bc5-a7e9-0e674ecdf52c",
    "timestamp": "2026-05-04T10:05:06.911668+00:00",
    "location": "Your house",
    "issue": "Your house is on fire.",
    "urgency": 4,
    "status": "Pending Dispatch"
  },
  {
    "id": "6027d311-92da-4d93-b16c-29979dad4ac9",
    "timestamp": "2026-05-04T10:06:44.642018+00:00",
    "location": "en",
    "issue": "We hope this interview will be useful and helpful for you.",
    "urgency": 1,
    "status": "Pending Dispatch"
  },
  {
    "id": "e94ebfc3-a8ff-4765-b1ca-3afc21afa4bc",
    "timestamp": "2026-05-04T10:11:13.989013+00:00",
    "location": "en",
    "issue": "My house is on fire.",
    "urgency": 4,
    "status": "Pending Dispatch"
  },
  {
    "id": "ffd45807-ec53-4071-b2b6-400520a5931b",
    "timestamp": "2026-05-04T10:27:37.922393+00:00",
    "location": "your house",
    "issue": "Is there a fire in your house?",
    "urgency": 4,
    "status": "Pending Dispatch"
  },
  {
    "id": "85e7c6cf-a517-49dd-806f-093fd001b0a4",
    "timestamp": "2026-05-04T10:30:00.692665+00:00",
    "location": "Majestic bus stand",
    "issue": "You were hit by a car and are injured, is that correct?",
    "urgency": 3,
    "status": "Pending Dispatch"
  },
  {
    "id": "de86308b-ebbd-48d8-877e-9588d26175d5",
    "timestamp": "2026-05-04T10:32:39.182837+00:00",
    "location": "Majestic Bus Stand, Bengaluru",
    "issue": "You were hit by a car at Majestic Bus Stand in Bengaluru, is that correct?",
    "urgency": 3,
    "status": "Pending Dispatch"
  },
  {
    "id": "05ae58d5-a9e3-42f6-a28e-395cb5d49843",
    "timestamp": "2026-05-04T10:45:41.582180+00:00",
    "location": "your house",
    "issue": "There's a fire in your house.",
    "urgency": 4,
    "status": "Pending Dispatch"
  },
  {
    "id": "9cbbd4e9-c596-41cf-a31e-506e58cc856a",
    "timestamp": "2026-05-04T11:12:56.641854+00:00",
    "location": "There is my location is",
    "issue": "I understand there is a Fire emergency at There is my location is. Is that correct?",
    "urgency": 4,
    "status": "Pending Dispatch"
  },
  {
    "id": "e9b1ad81-9a60-426d-a36d-c59d59a0840d",
    "timestamp": "2026-05-04T11:18:59.357491+00:00",
    "location": "प्राइंगलोरू सेक्टर बारा",
    "issue": "मुझे समझ आ रहा है कि प्राइंगलोरू सेक्टर बारा में आग की स्थिति है। क्या यह सही है?",
    "urgency": 4,
    "status": "Pending Dispatch"
  },
  {
    "session_id": "f387171e-ef39-4281-a868-da2ac054225f",
    "timestamp": "2026-05-04T11:39:51.010527+00:00",
    "location": "14 Bengaluru.",
    "complaint_text": "I understand there is a Water Issue emergency at 14 Bengaluru.. Is that correct?",
    "intent": "Water Issue",
    "urgency": 3,
    "distress_level": 2,
    "language": "en",
    "acoustic_data": {
      "environment": "quiet",
      "loudness": "normal"
    },
    "status": "Pending Dispatch"
  },
  {
    "session_id": "60f33b05-baae-4047-9ca7-cd9550793ac4",
    "timestamp": "2026-05-04T11:53:55.167940+00:00",
    "location": "my area",
    "complaint_text": "I understand there is a Water Issue emergency at my area. Is that correct?",
    "intent": "Water Issue",
    "urgency": 3,
    "distress_level": 2,
    "language": "en",
    "acoustic_data": {
      "environment": "moderate",
      "loudness": "normal"
    },
    "status": "Pending Dispatch"
  },
  {
    "session_id": "228e7327-e6a3-412c-9ff2-e27e21bae470",
    "timestamp": "2026-05-04T11:55:15.809514+00:00",
    "location": "مردانی نگر صحابے گاؤں",
    "complaint_text": "मुझे समझ आ रहा है कि مردانی نگر صحابے گاؤں में आपातस्थिति की स्थिति है। क्या यह सही है?",
    "intent": "Water issue",
    "urgency": 3,
    "distress_level": 3,
    "language": "hi",
    "acoustic_data": {
      "environment": "quiet",
      "loudness": "normal"
    },
    "status": "Pending Dispatch"
  },
  {
    "session_id": "e9ee5ba6-7253-439e-9dc6-13296a61dfd7",
    "timestamp": "2026-05-04T12:23:51.631655+00:00",
    "location": "my area",
    "complaint_text": "I understand there is a Water emergency at my area. Is that correct?",
    "intent": "Water",
    "urgency": 3,
    "distress_level": 1,
    "language": "en",
    "acoustic_data": {
      "environment": "moderate",
      "loudness": "normal"
    },
    "status": "Pending Dispatch"
  },
  {
    "session_id": "06982d22-7233-4acb-a314-4b92df2cb597",
    "timestamp": "2026-05-04T12:24:57.524836+00:00",
    "location": "دانی نگر",
    "complaint_text": "मुझे समझ आ रहा है कि دانی نگر में आपातस्थिति की स्थिति है। क्या यह सही है?",
    "intent": "water issue",
    "urgency": 3,
    "distress_level": 3,
    "language": "hi",
    "acoustic_data": {
      "environment": "quiet",
      "loudness": "normal"
    },
    "status": "Pending Dispatch"
  }
]